setup.py
open_korean_text_python.egg-info/PKG-INFO
open_korean_text_python.egg-info/SOURCES.txt
open_korean_text_python.egg-info/dependency_links.txt
open_korean_text_python.egg-info/requires.txt
open_korean_text_python.egg-info/top_level.txt
openkoreantext/__init__.py
openkoreantext/jvm.py
openkoreantext/jar/open-korean-text-2.1.2.jar
openkoreantext/jar/scala-library-2.12.4.jar
openkoreantext/jar/twitter-text-1.14.7.jar